CHANGELOG.md
LICENSE
MANIFEST.in
README.rst
setup.cfg
setup.py
tests/__init__.py
tests/test_blocks.py
tests/test_paginators.py
tests/test_templatetags.py
tests/test_widget.py
tests/testapp/__init__.py
tests/testapp/manage.py
tests/testapp/core/__init__.py
tests/testapp/core/models.py
tests/testapp/core/migrations/0001_initial.py
tests/testapp/core/migrations/__init__.py
tests/testapp/testapp/__init__.py
tests/testapp/testapp/settings.py
tests/testapp/testapp/urls.py
tests/testapp/testapp/wsgi.py
wagtailmodelchoosers/.DS_Store
wagtailmodelchoosers/__init__.py
wagtailmodelchoosers/blocks.py
wagtailmodelchoosers/edit_handlers.py
wagtailmodelchoosers/paginators.py
wagtailmodelchoosers/utils.py
wagtailmodelchoosers/views.py
wagtailmodelchoosers/wagtail_hooks.py
wagtailmodelchoosers/widgets.py
wagtailmodelchoosers.egg-info/PKG-INFO
wagtailmodelchoosers.egg-info/SOURCES.txt
wagtailmodelchoosers.egg-info/dependency_links.txt
wagtailmodelchoosers.egg-info/not-zip-safe
wagtailmodelchoosers.egg-info/requires.txt
wagtailmodelchoosers.egg-info/top_level.txt
wagtailmodelchoosers/client/.DS_Store
wagtailmodelchoosers/client/polyfills.js
wagtailmodelchoosers/client/utils.js
wagtailmodelchoosers/client/wagtailmodelchoosers.css
wagtailmodelchoosers/client/wagtailmodelchoosers.js
wagtailmodelchoosers/client/wagtailmodelchoosers.test.js
wagtailmodelchoosers/client/webpack.config.dev.js
wagtailmodelchoosers/client/webpack.config.prod.js
wagtailmodelchoosers/client/components/AutoComplete.js
wagtailmodelchoosers/client/components/BaseChooser.js
wagtailmodelchoosers/client/components/Buttons.js
wagtailmodelchoosers/client/components/ModelChooser.js
wagtailmodelchoosers/client/components/ModelPicker.js
wagtailmodelchoosers/client/components/RemoteModelChooser.js
wagtailmodelchoosers/client/sources/ModelSource.js
wagtailmodelchoosers/client/sources/RemoteModelSource.js
wagtailmodelchoosers/static/wagtailmodelchoosers/polyfills.js
wagtailmodelchoosers/static/wagtailmodelchoosers/wagtailmodelchoosers.css
wagtailmodelchoosers/static/wagtailmodelchoosers/wagtailmodelchoosers.js
wagtailmodelchoosers/templates/.DS_Store
wagtailmodelchoosers/templates/wagtailmodelchoosers/.DS_Store
